ssb_libtest76/__init__.py
ssb_libtest76/__main__.py
ssb_libtest76/functions.py
ssb_libtest76/py.typed
ssb_libtest76-0.0.1.dist-info/LICENSE
ssb_libtest76-0.0.1.dist-info/METADATA
ssb_libtest76-0.0.1.dist-info/WHEEL
ssb_libtest76-0.0.1.dist-info/entry_points.txt
ssb_libtest76-0.0.1.dist-info/RECORD
